Metadata-Version: 1.2
Name: pyTTF
Version: 3.0.0
Summary: A way to create script TerraForn Template for the bank
Home-page: https://github.com/batestin1/
Author: Maycon Cypriano Batestin
Author-email: mayconcipriano@gmail.com
License: UNKNOWN
Project-URL: Código fonte, https://github.com/batestin1/
Project-URL: Download, https://github.com/batestin1/
Keywords: A way to create script TerraForn Template for the bank
Platform: UNKNOWN
